huobiApi/__init__.py
huobiApi/config.py
huobiApi/service.py
huobiApi/utils.py
huobiApi-0.0.5.dist-info/LICENSE
huobiApi-0.0.5.dist-info/METADATA
huobiApi-0.0.5.dist-info/WHEEL
huobiApi-0.0.5.dist-info/top_level.txt
huobiApi-0.0.5.dist-info/RECORD
