Metadata-Version: 2.1
Name: huobiApi
Version: 0.0.5
Summary: helper functions of huobi rest api
Home-page: https://github.com/MJeremy2017/HuobiApi
Author: Jeremy.Zhang
Author-email: zhangyue9306@gmail.com
License: UNKNOWN
Platform: UNKNOWN
Classifier: Programming Language :: Python :: 3
Classifier: License :: OSI Approved :: MIT License
Classifier: Operating System :: OS Independent
Requires-Python: >=3.5
Requires-Dist: numpy
Requires-Dist: requests
Requires-Dist: pandas
